longdata/__init__.py
longdata/agent_router_chain.py
longdata/anage_agent.py
longdata/geneage_agent.py
longdata/longevity_data_chain.py
longdata/longevitymap_agent.py
longdata/util.py
longdata-0.0.3.dist-info/LICENSE
longdata-0.0.3.dist-info/METADATA
longdata-0.0.3.dist-info/WHEEL
longdata-0.0.3.dist-info/top_level.txt
longdata-0.0.3.dist-info/RECORD
