Metadata-Version: 2.1
Name: longdata
Version: 0.0.3
Summary: longevity-databases - longdata to work with common databases
Author: Alex Karmazin
Author-email: <karmazinalex@gmail.com>
Keywords: python,utils,files,papers,download,longevity databases
Classifier: Development Status :: 2 - Pre-Alpha
Classifier: Intended Audience :: Developers
Classifier: Programming Language :: Python :: 3.10
Classifier: Programming Language :: Python :: 3.11
Classifier: Operating System :: Unix
Classifier: Operating System :: MacOS :: MacOS X
Classifier: Operating System :: Microsoft :: Windows
License-File: LICENSE
Requires-Dist: pyfunctional
Requires-Dist: pycomfort
Requires-Dist: more-itertools
Requires-Dist: click
Requires-Dist: python-dotenv
Requires-Dist: tiktoken
Requires-Dist: langchain
Requires-Dist: openai
Requires-Dist: Deprecated
Requires-Dist: loguru
Requires-Dist: sentence-transformers
Requires-Dist: datasets
Requires-Dist: polars
Requires-Dist: python-Levenshtein
